circuits/full_adder.v
module FullAdder(
    input a,
    input b,
    input cin,
    output cout,
    output sum
    );

    assign sum = (a^b^cin);
    assign cout = (a&b) | (a&cin)| (b&cin);
    
endmodule

circuits/adder.v
`include "../circuits/full_adder.v"

module Adder
    #(parameter n=4)
    (
    input [n-1:0] augend,
    input [n-1:0] addend,
    output [n:0] final_sum
    );

    wire [n:0] carries;
    wire [n-1:0] sums;

    assign carries[0] = 1'b0;

    genvar i;
    generate
        for(i=0; i <n; i=i+1) begin
            FullAdder full_adder_gen(.a(augend[i]),.b(addend[i]),.cin(carries[i]),.cout(carries[i+1]),.sum(sums[i]));
        end
    endgenerate

    assign final_sum[n-1:0] = sums;
    assign final_sum[n] = carries[n];

endmodule

testbenches/adder_tb.v
`timescale 1ns/1ns
`include "../circuits/adder.v"

module AdderTB
    #(parameter n = 4)
    (
    output reg [n-1:0] augend,
    output reg [n-1:0] addend,
    input [n:0] final_sum
    );
    integer i;
    integer j;
    Adder #(.n(n)) dutAdder(.augend(augend),.addend(addend),.final_sum(final_sum));

    initial begin
        $dumpfile("adder_tb.vcd");
        $dumpvars(0, AdderTB);

        augend = 4'b0;
        addend = 4'b0;

        $monitor($time, " augend=%b, addend=%b, final_sum=%b", augend, addend, final_sum);
        for(i=0; i <2**n; i=i+1) begin
            #10;
            for(j=0; j <2**n; j=j+1) begin
                #10;     
                addend = addend + 1'b1;   
            end
            augend = augend + 1'b1;
        end

        #10 $display("Test Complete!");
        #10 $finish;     
    end
endmodule

testbenches/adder_tb.vcd
$date
	Tue May 17 00:35:54 2022
$end
$version
	Icarus Verilog
$end
$timescale
	1ns
$end
$scope module AdderTB $end
$var wire 5 ! final_sum [4:0] $end
$var reg 4 " addend [3:0] $end
$var reg 4 # augend [3:0] $end
$var integer 32 $ i [31:0] $end
$var integer 32 % j [31:0] $end
$scope module dutAdder $end
$var wire 4 & addend [3:0] $end
$var wire 4 ' augend [3:0] $end
$var wire 4 ( sums [3:0] $end
$var wire 5 ) final_sum [4:0] $end
$var wire 5 * carries [4:0] $end
$scope begin genblk1[0] $end
$scope module full_adder_gen $end
$var wire 1 + a $end
$var wire 1 , b $end
$var wire 1 - cin $end
$var wire 1 . cout $end
$var wire 1 / sum $end
$upscope $end
$upscope $end
$scope begin genblk1[1] $end
$scope module full_adder_gen $end
$var wire 1 0 a $end
$var wire 1 1 b $end
$var wire 1 2 cin $end
$var wire 1 3 cout $end
$var wire 1 4 sum $end
$upscope $end
$upscope $end
$scope begin genblk1[2] $end
$scope module full_adder_gen $end
$var wire 1 5 a $end
$var wire 1 6 b $end
$var wire 1 7 cin $end
$var wire 1 8 cout $end
$var wire 1 9 sum $end
$upscope $end
$upscope $end
$scope begin genblk1[3] $end
$scope module full_adder_gen $end
$var wire 1 : a $end
$var wire 1 ; b $end
$var wire 1 < cin $end
$var wire 1 = cout $end
$var wire 1 > sum $end
$upscope $end
$upscope $end
$upscope $end
$upscope $end
$enddefinitions $end
#0
$dumpvars
0>
0=
0<
0;
0:
09
08
07
06
05
04
03
02
01
00
0/
0.
0-
0,
0+
b0 *
b0 )
b0 (
b0 '
b0 &
bx %
b0 $
b0 #
b0 "
b0 !
$end
#10
b0 %
#20
b1 !
b1 )
b1 (
1/
1,
b1 %
b1 "
b1 &
#30
0/
b10 !
b10 )
b10 (
14
0,
11
b10 %
b10 "
b10 &
#40
b11 !
b11 )
b11 (
1/
1,
b11 %
b11 "
b11 &
#50
0/
04
b100 !
b100 )
b100 (
19
0,
01
16
b100 %
b100 "
b100 &
#60
b101 !
b101 )
b101 (
1/
1,
b101 %
b101 "
b101 &
#70
0/
b110 !
b110 )
b110 (
14
0,
11
b110 %
b110 "
b110 &
#80
b111 !
b111 )
b111 (
1/
1,
b111 %
b111 "
b111 &
#90
0/
04
09
b1000 !
b1000 )
b1000 (
1>
0,
01
06
1;
b1000 %
b1000 "
b1000 &
#100
b1001 !
b1001 )
b1001 (
1/
1,
b1001 %
b1001 "
b1001 &
#110
0/
b1010 !
b1010 )
b1010 (
14
0,
11
b1010 %
b1010 "
b1010 &
#120
b1011 !
b1011 )
b1011 (
1/
1,
b1011 %
b1011 "
b1011 &
#130
0/
04
b1100 !
b1100 )
b1100 (
19
0,
01
16
b1100 %
b1100 "
b1100 &
#140
b1101 !
b1101 )
b1101 (
1/
1,
b1101 %
b1101 "
b1101 &
#150
0/
b1110 !
b1110 )
b1110 (
14
0,
11
b1110 %
b1110 "
b1110 &
#160
b1111 !
b1111 )
b1111 (
1/
1,
b1111 %
b1111 "
b1111 &
#170
04
09
b1 !
b1 )
b1 (
0>
1+
0,
01
06
0;
b1 $
b1 #
b1 '
b10000 %
b0 "
b0 &
#180
b0 %
#190
14
12
b10 *
1.
b10 !
b10 )
b10 (
0/
1,
b1 %
b1 "
b1 &
#200
02
09
0.
07
1/
b11 !
b11 )
b11 (
14
b0 *
03
0,
11
b10 %
b10 "
b10 &
#210
19
17
13
04
12
b110 *
1.
b100 !
b100 )
b100 (
0/
1,
b11 %
b11 "
b11 &
#220
02
0>
0.
07
0<
1/
04
03
b101 !
b101 )
b101 (
19
b0 *
08
0,
01
16
b100 %
b100 "
b100 &
#230
14
12
b10 *
1.
b110 !
b110 )
b110 (
0/
1,
b101 %
b101 "
b101 &
#240
0>
0<
08
02
19
0.
07
1/
b111 !
b111 )
b111 (
14
b0 *
03
0,
11
b110 %
b110 "
b110 &
#250
1>
1<
18
09
17
13
04
12
b1110 *
1.
b1000 !
b1000 )
b1000 (
0/
1,
b111 %
b111 "
b111 &
#260
02
0.
07
0<
1/
04
03
09
08
b1001 !
b1001 )
b1001 (
1>
b0 *
0=
0,
01
06
1;
b1000 %
b1000 "
b1000 &
#270
14
12
b10 *
1.
b1010 !
b1010 )
b1010 (
0/
1,
b1001 %
b1001 "
b1001 &
#280
02
09
0.
07
1/
b1011 !
b1011 )
b1011 (
14
b0 *
03
0,
11
b1010 %
b1010 "
b1010 &
#290
19
17
13
04
12
b110 *
1.
b1100 !
b1100 )
b1100 (
0/
1,
b1011 %
b1011 "
b1011 &
#300
0=
02
1>
0.
07
0<
1/
04
03
b1101 !
b1101 )
b1101 (
19
b0 *
08
0,
01
16
b1100 %
b1100 "
b1100 &
#310
14
12
b10 *
1.
b1110 !
b1110 )
b1110 (
0/
1,
b1101 %
b1101 "
b1101 &
#320
0=
1>
0<
08
02
19
0.
07
1/
b1111 !
b1111 )
b1111 (
14
b0 *
03
0,
11
b1110 %
b1110 "
b1110 &
#330
1=
0>
1<
18
09
17
13
04
12
b11110 *
1.
b10000 !
b10000 )
b0 (
0/
1,
b1111 %
b1111 "
b1111 &
#340
14
02
0.
07
0<
03
09
08
b10 !
b10 )
b10 (
0>
b0 *
0=
0+
10
0,
01
06
0;
b10 $
b10 #
b10 '
b10000 %
b0 "
b0 &
#350
b0 %
#360
b11 !
b11 )
b11 (
1/
1,
b1 %
b1 "
b1 &
#370
19
17
b100 *
13
0/
b100 !
b100 )
b100 (
04
0,
11
b10 %
b10 "
b10 &
#380
b101 !
b101 )
b101 (
1/
1,
b11 %
b11 "
b11 &
#390
07
0>
03
0<
0/
14
b110 !
b110 )
b110 (
19
b0 *
08
0,
01
16
b100 %
b100 "
b100 &
#400
b111 !
b111 )
b111 (
1/
1,
b101 %
b101 "
b101 &
#410
1>
1<
18
09
17
b1100 *
13
0/
b1000 !
b1000 )
b1000 (
04
0,
11
b110 %
b110 "
b110 &
#420
b1001 !
b1001 )
b1001 (
1/
1,
b111 %
b111 "
b111 &
#430
07
03
0<
0/
14
09
08
b1010 !
b1010 )
b1010 (
1>
b0 *
0=
0,
01
06
1;
b1000 %
b1000 "
b1000 &
#440
b1011 !
b1011 )
b1011 (
1/
1,
b1001 %
b1001 "
b1001 &
#450
19
17
b100 *
13
0/
b1100 !
b1100 )
b1100 (
04
0,
11
b1010 %
b1010 "
b1010 &
#460
b1101 !
b1101 )
b1101 (
1/
1,
b1011 %
b1011 "
b1011 &
#470
0=
07
1>
03
0<
0/
14
b1110 !
b1110 )
b1110 (
19
b0 *
08
0,
01
16
b1100 %
b1100 "
b1100 &
#480
b1111 !
b1111 )
b1111 (
1/
1,
b1101 %
b1101 "
b1101 &
#490
1=
0>
1<
18
09
17
b11100 *
13
0/
b10000 !
b10000 )
b0 (
04
0,
11
b1110 %
b1110 "
b1110 &
#500
b10001 !
b10001 )
b1 (
1/
1,
b1111 %
b1111 "
b1111 &
#510
07
03
0<
14
09
08
b11 !
b11 )
b11 (
0>
b0 *
0=
1+
0,
01
06
0;
b11 $
b11 #
b11 '
b10000 %
b0 "
b0 &
#520
b0 %
#530
19
17
13
04
12
b110 *
1.
b100 !
b100 )
b100 (
0/
1,
b1 %
b1 "
b1 &
#540
02
b100 *
0.
1/
b101 !
b101 )
b101 (
04
0,
11
b10 %
b10 "
b10 &
#550
14
12
b110 *
1.
b110 !
b110 )
b110 (
0/
1,
b11 %
b11 "
b11 &
#560
07
03
02
0>
0.
0<
1/
14
b111 !
b111 )
b111 (
19
b0 *
08
0,
01
16
b100 %
b100 "
b100 &
#570
1>
1<
18
09
17
13
04
12
b1110 *
1.
b1000 !
b1000 )
b1000 (
0/
1,
b101 %
b101 "
b101 &
#580
02
b1100 *
0.
1/
b1001 !
b1001 )
b1001 (
04
0,
11
b110 %
b110 "
b110 &
#590
14
12
b1110 *
1.
b1010 !
b1010 )
b1010 (
0/
1,
b111 %
b111 "
b111 &
#600
07
03
02
0.
0<
1/
14
09
08
b1011 !
b1011 )
b1011 (
1>
b0 *
0=
0,
01
06
1;
b1000 %
b1000 "
b1000 &
#610
19
17
13
04
12
b110 *
1.
b1100 !
b1100 )
b1100 (
0/
1,
b1001 %
b1001 "
b1001 &
#620
02
b100 *
0.
1/
b1101 !
b1101 )
b1101 (
04
0,
11
b1010 %
b1010 "
b1010 &
#630
14
12
b110 *
1.
b1110 !
b1110 )
b1110 (
0/
1,
b1011 %
b1011 "
b1011 &
#640
07
03
0=
02
1>
0.
0<
1/
14
b1111 !
b1111 )
b1111 (
19
b0 *
08
0,
01
16
b1100 %
b1100 "
b1100 &
#650
1=
0>
1<
18
09
17
13
04
12
b11110 *
1.
b10000 !
b10000 )
b0 (
0/
1,
b1101 %
b1101 "
b1101 &
#660
02
b11100 *
0.
1/
b10001 !
b10001 )
b1 (
04
0,
11
b1110 %
b1110 "
b1110 &
#670
14
12
b11110 *
1.
b10010 !
b10010 )
b10 (
0/
1,
b1111 %
b1111 "
b1111 &
#680
04
19
02
07
0.
03
0<
08
b100 !
b100 )
b100 (
0>
b0 *
0=
0+
00
15
0,
01
06
0;
b100 $
b100 #
b100 '
b10000 %
b0 "
b0 &
#690
b0 %
#700
b101 !
b101 )
b101 (
1/
1,
b1 %
b1 "
b1 &
#710
0/
b110 !
b110 )
b110 (
14
0,
11
b10 %
b10 "
b10 &
#720
b111 !
b111 )
b111 (
1/
1,
b11 %
b11 "
b11 &
#730
1>
1<
b1000 *
18
0/
04
b1000 !
b1000 )
b1000 (
09
0,
01
16
b100 %
b100 "
b100 &
#740
b1001 !
b1001 )
b1001 (
1/
1,
b101 %
b101 "
b101 &
#750
0/
b1010 !
b1010 )
b1010 (
14
0,
11
b110 %
b110 "
b110 &
#760
b1011 !
b1011 )
b1011 (
1/
1,
b111 %
b111 "
b111 &
#770
0<
08
0/
04
19
b1100 !
b1100 )
b1100 (
1>
b0 *
0=
0,
01
06
1;
b1000 %
b1000 "
b1000 &
#780
b1101 !
b1101 )
b1101 (
1/
1,
b1001 %
b1001 "
b1001 &
#790
0/
b1110 !
b1110 )
b1110 (
14
0,
11
b1010 %
b1010 "
b1010 &
#800
b1111 !
b1111 )
b1111 (
1/
1,
b1011 %
b1011 "
b1011 &
#810
1=
0>
1<
b11000 *
18
0/
04
b10000 !
b10000 )
b0 (
09
0,
01
16
b1100 %
b1100 "
b1100 &
#820
b10001 !
b10001 )
b1 (
1/
1,
b1101 %
b1101 "
b1101 &
#830
0/
b10010 !
b10010 )
b10 (
14
0,
11
b1110 %
b1110 "
b1110 &
#840
b10011 !
b10011 )
b11 (
1/
1,
b1111 %
b1111 "
b1111 &
#850
0<
08
04
19
b101 !
b101 )
b101 (
0>
b0 *
0=
1+
0,
01
06
0;
b101 $
b101 #
b101 '
b10000 %
b0 "
b0 &
#860
b0 %
#870
14
12
b10 *
1.
b110 !
b110 )
b110 (
0/
1,
b1 %
b1 "
b1 &
#880
0>
0<
08
02
19
0.
07
1/
b111 !
b111 )
b111 (
14
b0 *
03
0,
11
b10 %
b10 "
b10 &
#890
1>
1<
18
09
17
13
04
12
b1110 *
1.
b1000 !
b1000 )
b1000 (
0/
1,
b11 %
b11 "
b11 &
#900
02
0.
07
1/
04
b1000 *
03
b1001 !
b1001 )
b1001 (
09
0,
01
16
b100 %
b100 "
b100 &
#910
14
12
b1010 *
1.
b1010 !
b1010 )
b1010 (
0/
1,
b101 %
b101 "
b101 &
#920
02
09
0.
07
1/
b1011 !
b1011 )
b1011 (
14
b1000 *
03
0,
11
b110 %
b110 "
b110 &
#930
19
17
13
04
12
b1110 *
1.
b1100 !
b1100 )
b1100 (
0/
1,
b111 %
b111 "
b111 &
#940
0<
08
02
0.
07
1/
04
03
19
b1101 !
b1101 )
b1101 (
1>
b0 *
0=
0,
01
06
1;
b1000 %
b1000 "
b1000 &
#950
14
12
b10 *
1.
b1110 !
b1110 )
b1110 (
0/
1,
b1001 %
b1001 "
b1001 &
#960
0=
1>
0<
08
02
19
0.
07
1/
b1111 !
b1111 )
b1111 (
14
b0 *
03
0,
11
b1010 %
b1010 "
b1010 &
#970
1=
0>
1<
18
09
17
13
04
12
b11110 *
1.
b10000 !
b10000 )
b0 (
0/
1,
b1011 %
b1011 "
b1011 &
#980
02
0.
07
1/
04
b11000 *
03
b10001 !
b10001 )
b1 (
09
0,
01
16
b1100 %
b1100 "
b1100 &
#990
14
12
b11010 *
1.
b10010 !
b10010 )
b10 (
0/
1,
b1101 %
b1101 "
b1101 &
#1000
02
09
0.
07
1/
b10011 !
b10011 )
b11 (
14
b11000 *
03
0,
11
b1110 %
b1110 "
b1110 &
#1010
19
17
13
04
12
b11110 *
1.
b10100 !
b10100 )
b100 (
0/
1,
b1111 %
b1111 "
b1111 &
#1020
0<
08
14
02
0.
07
03
19
b110 !
b110 )
b110 (
0>
b0 *
0=
0+
10
0,
01
06
0;
b110 $
b110 #
b110 '
b10000 %
b0 "
b0 &
#1030
b0 %
#1040
b111 !
b111 )
b111 (
1/
1,
b1 %
b1 "
b1 &
#1050
1>
1<
18
09
17
b1100 *
13
0/
b1000 !
b1000 )
b1000 (
04
0,
11
b10 %
b10 "
b10 &
#1060
b1001 !
b1001 )
b1001 (
1/
1,
b11 %
b11 "
b11 &
#1070
07
b1000 *
03
0/
14
b1010 !
b1010 )
b1010 (
09
0,
01
16
b100 %
b100 "
b100 &
#1080
b1011 !
b1011 )
b1011 (
1/
1,
b101 %
b101 "
b101 &
#1090
19
17
b1100 *
13
0/
b1100 !
b1100 )
b1100 (
04
0,
11
b110 %
b110 "
b110 &
#1100
b1101 !
b1101 )
b1101 (
1/
1,
b111 %
b111 "
b111 &
#1110
0<
08
07
03
0/
14
19
b1110 !
b1110 )
b1110 (
1>
b0 *
0=
0,
01
06
1;
b1000 %
b1000 "
b1000 &
#1120
b1111 !
b1111 )
b1111 (
1/
1,
b1001 %
b1001 "
b1001 &
#1130
1=
0>
1<
18
09
17
b11100 *
13
0/
b10000 !
b10000 )
b0 (
04
0,
11
b1010 %
b1010 "
b1010 &
#1140
b10001 !
b10001 )
b1 (
1/
1,
b1011 %
b1011 "
b1011 &
#1150
07
b11000 *
03
0/
14
b10010 !
b10010 )
b10 (
09
0,
01
16
b1100 %
b1100 "
b1100 &
#1160
b10011 !
b10011 )
b11 (
1/
1,
b1101 %
b1101 "
b1101 &
#1170
19
17
b11100 *
13
0/
b10100 !
b10100 )
b100 (
04
0,
11
b1110 %
b1110 "
b1110 &
#1180
b10101 !
b10101 )
b101 (
1/
1,
b1111 %
b1111 "
b1111 &
#1190
0<
08
07
03
14
19
b111 !
b111 )
b111 (
0>
b0 *
0=
1+
0,
01
06
0;
b111 $
b111 #
b111 '
b10000 %
b0 "
b0 &
#1200
b0 %
#1210
1>
1<
18
09
17
13
04
12
b1110 *
1.
b1000 !
b1000 )
b1000 (
0/
1,
b1 %
b1 "
b1 &
#1220
02
b1100 *
0.
1/
b1001 !
b1001 )
b1001 (
04
0,
11
b10 %
b10 "
b10 &
#1230
14
12
b1110 *
1.
b1010 !
b1010 )
b1010 (
0/
1,
b11 %
b11 "
b11 &
#1240
07
03
02
b1000 *
0.
1/
14
b1011 !
b1011 )
b1011 (
09
0,
01
16
b100 %
b100 "
b100 &
#1250
19
17
13
04
12
b1110 *
1.
b1100 !
b1100 )
b1100 (
0/
1,
b101 %
b101 "
b101 &
#1260
02
b1100 *
0.
1/
b1101 !
b1101 )
b1101 (
04
0,
11
b110 %
b110 "
b110 &
#1270
14
12
b1110 *
1.
b1110 !
b1110 )
b1110 (
0/
1,
b111 %
b111 "
b111 &
#1280
0<
08
07
03
02
0.
1/
14
19
b1111 !
b1111 )
b1111 (
1>
b0 *
0=
0,
01
06
1;
b1000 %
b1000 "
b1000 &
#1290
1=
0>
1<
18
09
17
13
04
12
b11110 *
1.
b10000 !
b10000 )
b0 (
0/
1,
b1001 %
b1001 "
b1001 &
#1300
02
b11100 *
0.
1/
b10001 !
b10001 )
b1 (
04
0,
11
b1010 %
b1010 "
b1010 &
#1310
14
12
b11110 *
1.
b10010 !
b10010 )
b10 (
0/
1,
b1011 %
b1011 "
b1011 &
#1320
07
03
02
b11000 *
0.
1/
14
b10011 !
b10011 )
b11 (
09
0,
01
16
b1100 %
b1100 "
b1100 &
#1330
19
17
13
04
12
b11110 *
1.
b10100 !
b10100 )
b100 (
0/
1,
b1101 %
b1101 "
b1101 &
#1340
02
b11100 *
0.
1/
b10101 !
b10101 )
b101 (
04
0,
11
b1110 %
b1110 "
b1110 &
#1350
14
12
b11110 *
1.
b10110 !
b10110 )
b110 (
0/
1,
b1111 %
b1111 "
b1111 &
#1360
04
09
b1000 (
1>
02
07
0<
0.
03
08
b1000 !
b1000 )
b0 *
0=
0+
00
05
1:
0,
01
06
0;
b1000 $
b1000 #
b1000 '
b10000 %
b0 "
b0 &
#1370
b0 %
#1380
b1001 !
b1001 )
b1001 (
1/
1,
b1 %
b1 "
b1 &
#1390
0/
b1010 !
b1010 )
b1010 (
14
0,
11
b10 %
b10 "
b10 &
#1400
b1011 !
b1011 )
b1011 (
1/
1,
b11 %
b11 "
b11 &
#1410
0/
04
b1100 !
b1100 )
b1100 (
19
0,
01
16
b100 %
b100 "
b100 &
#1420
b1101 !
b1101 )
b1101 (
1/
1,
b101 %
b101 "
b101 &
#1430
0/
b1110 !
b1110 )
b1110 (
14
0,
11
b110 %
b110 "
b110 &
#1440
b1111 !
b1111 )
b1111 (
1/
1,
b111 %
b111 "
b111 &
#1450
b10000 *
1=
0/
04
09
b10000 !
b10000 )
b0 (
0>
0,
01
06
1;
b1000 %
b1000 "
b1000 &
#1460
b10001 !
b10001 )
b1 (
1/
1,
b1001 %
b1001 "
b1001 &
#1470
0/
b10010 !
b10010 )
b10 (
14
0,
11
b1010 %
b1010 "
b1010 &
#1480
b10011 !
b10011 )
b11 (
1/
1,
b1011 %
b1011 "
b1011 &
#1490
0/
04
b10100 !
b10100 )
b100 (
19
0,
01
16
b1100 %
b1100 "
b1100 &
#1500
b10101 !
b10101 )
b101 (
1/
1,
b1101 %
b1101 "
b1101 &
#1510
0/
b10110 !
b10110 )
b110 (
14
0,
11
b1110 %
b1110 "
b1110 &
#1520
b10111 !
b10111 )
b111 (
1/
1,
b1111 %
b1111 "
b1111 &
#1530
b0 *
0=
04
09
b1001 !
b1001 )
b1001 (
1>
1+
0,
01
06
0;
b1001 $
b1001 #
b1001 '
b10000 %
b0 "
b0 &
#1540
b0 %
#1550
14
12
b10 *
1.
b1010 !
b1010 )
b1010 (
0/
1,
b1 %
b1 "
b1 &
#1560
02
09
0.
07
1/
b1011 !
b1011 )
b1011 (
14
b0 *
03
0,
11
b10 %
b10 "
b10 &
#1570
19
17
13
04
12
b110 *
1.
b1100 !
b1100 )
b1100 (
0/
1,
b11 %
b11 "
b11 &
#1580
0=
02
1>
0.
07
0<
1/
04
03
b1101 !
b1101 )
b1101 (
19
b0 *
08
0,
01
16
b100 %
b100 "
b100 &
#1590
14
12
b10 *
1.
b1110 !
b1110 )
b1110 (
0/
1,
b101 %
b101 "
b101 &
#1600
0=
1>
0<
08
02
19
0.
07
1/
b1111 !
b1111 )
b1111 (
14
b0 *
03
0,
11
b110 %
b110 "
b110 &
#1610
1=
0>
1<
18
09
17
13
04
12
b11110 *
1.
b10000 !
b10000 )
b0 (
0/
1,
b111 %
b111 "
b111 &
#1620
02
0.
07
0<
1/
04
03
09
b10000 *
08
b10001 !
b10001 )
b1 (
0>
0,
01
06
1;
b1000 %
b1000 "
b1000 &
#1630
14
12
b10010 *
1.
b10010 !
b10010 )
b10 (
0/
1,
b1001 %
b1001 "
b1001 &
#1640
02
09
0.
07
1/
b10011 !
b10011 )
b11 (
14
b10000 *
03
0,
11
b1010 %
b1010 "
b1010 &
#1650
19
17
13
04
12
b10110 *
1.
b10100 !
b10100 )
b100 (
0/
1,
b1011 %
b1011 "
b1011 &
#1660
02
0>
0.
07
0<
1/
04
03
b10101 !
b10101 )
b101 (
19
b10000 *
08
0,
01
16
b1100 %
b1100 "
b1100 &
#1670
14
12
b10010 *
1.
b10110 !
b10110 )
b110 (
0/
1,
b1101 %
b1101 "
b1101 &
#1680
0>
0<
08
02
19
0.
07
1/
b10111 !
b10111 )
b111 (
14
b10000 *
03
0,
11
b1110 %
b1110 "
b1110 &
#1690
1>
1<
18
09
17
13
04
12
b11110 *
1.
b11000 !
b11000 )
b1000 (
0/
1,
b1111 %
b1111 "
b1111 &
#1700
0=
14
02
0.
07
0<
03
09
b0 *
08
b1010 !
b1010 )
b1010 (
1>
0+
10
0,
01
06
0;
b1010 $
b1010 #
b1010 '
b10000 %
b0 "
b0 &
#1710
b0 %
#1720
b1011 !
b1011 )
b1011 (
1/
1,
b1 %
b1 "
b1 &
#1730
19
17
b100 *
13
0/
b1100 !
b1100 )
b1100 (
04
0,
11
b10 %
b10 "
b10 &
#1740
b1101 !
b1101 )
b1101 (
1/
1,
b11 %
b11 "
b11 &
#1750
0=
07
1>
03
0<
0/
14
b1110 !
b1110 )
b1110 (
19
b0 *
08
0,
01
16
b100 %
b100 "
b100 &
#1760
b1111 !
b1111 )
b1111 (
1/
1,
b101 %
b101 "
b101 &
#1770
1=
0>
1<
18
09
17
b11100 *
13
0/
b10000 !
b10000 )
b0 (
04
0,
11
b110 %
b110 "
b110 &
#1780
b10001 !
b10001 )
b1 (
1/
1,
b111 %
b111 "
b111 &
#1790
07
03
0<
0/
14
09
b10000 *
08
b10010 !
b10010 )
b10 (
0>
0,
01
06
1;
b1000 %
b1000 "
b1000 &
#1800
b10011 !
b10011 )
b11 (
1/
1,
b1001 %
b1001 "
b1001 &
#1810
19
17
b10100 *
13
0/
b10100 !
b10100 )
b100 (
04
0,
11
b1010 %
b1010 "
b1010 &
#1820
b10101 !
b10101 )
b101 (
1/
1,
b1011 %
b1011 "
b1011 &
#1830
07
0>
03
0<
0/
14
b10110 !
b10110 )
b110 (
19
b10000 *
08
0,
01
16
b1100 %
b1100 "
b1100 &
#1840
b10111 !
b10111 )
b111 (
1/
1,
b1101 %
b1101 "
b1101 &
#1850
1>
1<
18
09
17
b11100 *
13
0/
b11000 !
b11000 )
b1000 (
04
0,
11
b1110 %
b1110 "
b1110 &
#1860
b11001 !
b11001 )
b1001 (
1/
1,
b1111 %
b1111 "
b1111 &
#1870
0=
07
03
0<
14
09
b0 *
08
b1011 !
b1011 )
b1011 (
1>
1+
0,
01
06
0;
b1011 $
b1011 #
b1011 '
b10000 %
b0 "
b0 &
#1880
b0 %
#1890
19
17
13
04
12
b110 *
1.
b1100 !
b1100 )
b1100 (
0/
1,
b1 %
b1 "
b1 &
#1900
02
b100 *
0.
1/
b1101 !
b1101 )
b1101 (
04
0,
11
b10 %
b10 "
b10 &
#1910
14
12
b110 *
1.
b1110 !
b1110 )
b1110 (
0/
1,
b11 %
b11 "
b11 &
#1920
07
03
0=
02
1>
0.
0<
1/
14
b1111 !
b1111 )
b1111 (
19
b0 *
08
0,
01
16
b100 %
b100 "
b100 &
#1930
1=
0>
1<
18
09
17
13
04
12
b11110 *
1.
b10000 !
b10000 )
b0 (
0/
1,
b101 %
b101 "
b101 &
#1940
02
b11100 *
0.
1/
b10001 !
b10001 )
b1 (
04
0,
11
b110 %
b110 "
b110 &
#1950
14
12
b11110 *
1.
b10010 !
b10010 )
b10 (
0/
1,
b111 %
b111 "
b111 &
#1960
07
03
02
0.
0<
1/
14
09
b10000 *
08
b10011 !
b10011 )
b11 (
0>
0,
01
06
1;
b1000 %
b1000 "
b1000 &
#1970
19
17
13
04
12
b10110 *
1.
b10100 !
b10100 )
b100 (
0/
1,
b1001 %
b1001 "
b1001 &
#1980
02
b10100 *
0.
1/
b10101 !
b10101 )
b101 (
04
0,
11
b1010 %
b1010 "
b1010 &
#1990
14
12
b10110 *
1.
b10110 !
b10110 )
b110 (
0/
1,
b1011 %
b1011 "
b1011 &
#2000
07
03
02
0>
0.
0<
1/
14
b10111 !
b10111 )
b111 (
19
b10000 *
08
0,
01
16
b1100 %
b1100 "
b1100 &
#2010
1>
1<
18
09
17
13
04
12
b11110 *
1.
b11000 !
b11000 )
b1000 (
0/
1,
b1101 %
b1101 "
b1101 &
#2020
02
b11100 *
0.
1/
b11001 !
b11001 )
b1001 (
04
0,
11
b1110 %
b1110 "
b1110 &
#2030
14
12
b11110 *
1.
b11010 !
b11010 )
b1010 (
0/
1,
b1111 %
b1111 "
b1111 &
#2040
0=
04
19
02
07
0.
03
0<
b0 *
08
b1100 !
b1100 )
b1100 (
1>
0+
00
15
0,
01
06
0;
b1100 $
b1100 #
b1100 '
b10000 %
b0 "
b0 &
#2050
b0 %
#2060
b1101 !
b1101 )
b1101 (
1/
1,
b1 %
b1 "
b1 &
#2070
0/
b1110 !
b1110 )
b1110 (
14
0,
11
b10 %
b10 "
b10 &
#2080
b1111 !
b1111 )
b1111 (
1/
1,
b11 %
b11 "
b11 &
#2090
1=
0>
1<
b11000 *
18
0/
04
b10000 !
b10000 )
b0 (
09
0,
01
16
b100 %
b100 "
b100 &
#2100
b10001 !
b10001 )
b1 (
1/
1,
b101 %
b101 "
b101 &
#2110
0/
b10010 !
b10010 )
b10 (
14
0,
11
b110 %
b110 "
b110 &
#2120
b10011 !
b10011 )
b11 (
1/
1,
b111 %
b111 "
b111 &
#2130
0<
b10000 *
08
0/
04
19
b10100 !
b10100 )
b100 (
0>
0,
01
06
1;
b1000 %
b1000 "
b1000 &
#2140
b10101 !
b10101 )
b101 (
1/
1,
b1001 %
b1001 "
b1001 &
#2150
0/
b10110 !
b10110 )
b110 (
14
0,
11
b1010 %
b1010 "
b1010 &
#2160
b10111 !
b10111 )
b111 (
1/
1,
b1011 %
b1011 "
b1011 &
#2170
1>
1<
b11000 *
18
0/
04
b11000 !
b11000 )
b1000 (
09
0,
01
16
b1100 %
b1100 "
b1100 &
#2180
b11001 !
b11001 )
b1001 (
1/
1,
b1101 %
b1101 "
b1101 &
#2190
0/
b11010 !
b11010 )
b1010 (
14
0,
11
b1110 %
b1110 "
b1110 &
#2200
b11011 !
b11011 )
b1011 (
1/
1,
b1111 %
b1111 "
b1111 &
#2210
0=
0<
b0 *
08
04
19
b1101 !
b1101 )
b1101 (
1>
1+
0,
01
06
0;
b1101 $
b1101 #
b1101 '
b10000 %
b0 "
b0 &
#2220
b0 %
#2230
14
12
b10 *
1.
b1110 !
b1110 )
b1110 (
0/
1,
b1 %
b1 "
b1 &
#2240
0=
1>
0<
08
02
19
0.
07
1/
b1111 !
b1111 )
b1111 (
14
b0 *
03
0,
11
b10 %
b10 "
b10 &
#2250
1=
0>
1<
18
09
17
13
04
12
b11110 *
1.
b10000 !
b10000 )
b0 (
0/
1,
b11 %
b11 "
b11 &
#2260
02
0.
07
1/
04
b11000 *
03
b10001 !
b10001 )
b1 (
09
0,
01
16
b100 %
b100 "
b100 &
#2270
14
12
b11010 *
1.
b10010 !
b10010 )
b10 (
0/
1,
b101 %
b101 "
b101 &
#2280
02
09
0.
07
1/
b10011 !
b10011 )
b11 (
14
b11000 *
03
0,
11
b110 %
b110 "
b110 &
#2290
19
17
13
04
12
b11110 *
1.
b10100 !
b10100 )
b100 (
0/
1,
b111 %
b111 "
b111 &
#2300
0<
08
02
0.
07
1/
04
b10000 *
03
19
b10101 !
b10101 )
b101 (
0>
0,
01
06
1;
b1000 %
b1000 "
b1000 &
#2310
14
12
b10010 *
1.
b10110 !
b10110 )
b110 (
0/
1,
b1001 %
b1001 "
b1001 &
#2320
0>
0<
08
02
19
0.
07
1/
b10111 !
b10111 )
b111 (
14
b10000 *
03
0,
11
b1010 %
b1010 "
b1010 &
#2330
1>
1<
18
09
17
13
04
12
b11110 *
1.
b11000 !
b11000 )
b1000 (
0/
1,
b1011 %
b1011 "
b1011 &
#2340
02
0.
07
1/
04
b11000 *
03
b11001 !
b11001 )
b1001 (
09
0,
01
16
b1100 %
b1100 "
b1100 &
#2350
14
12
b11010 *
1.
b11010 !
b11010 )
b1010 (
0/
1,
b1101 %
b1101 "
b1101 &
#2360
02
09
0.
07
1/
b11011 !
b11011 )
b1011 (
14
b11000 *
03
0,
11
b1110 %
b1110 "
b1110 &
