circuits/full_adder.v
module FullAdder(
    input a,
    input b,
    input cin,
    output cout,
    output sum
    );

    assign sum = (a^b^cin);
    assign cout = (a&b) | (a&cin)| (b&cin);
    
endmodule

testbenches/full_adder_tb.v
`timescale 1ns/1ns
`include "../circuits/full_adder.v"


module FullAdderTB(
    output reg a,
    output reg b,
    output reg cin,
    input cout,
    input sum
);
    FullAdder dut1(.a(a),.b(b),.cin(cin),.cout(cout),.sum(sum));
    // FullAdder dut1(a,b,cin,cout,sum);

    initial begin
        $dumpfile("full_adder_tb.vcd");
        $dumpvars(0, FullAdderTB);

        a=0;
        b=0;
        cin=0;
        $monitor($time, "a=%b", "b=%b", "cin=%b", "cout=%b", "sum=%b", a, b, cin, cout, sum);
        #10 cin=0; b=0; a=1;
        #10 cin=0; b=1; a=0;
        #10 cin=0; b=1; a=1;
        #10 cin=1; b=0; a=0;
        #10 cin=1; b=0; a=1;
        #10 cin=1; b=1; a=0;
        #10 cin=1; b=1; a=1;
        #10 $display("Test Complete");
        #10 $finish;
    end
endmodule

testbenches/full_adder_tb.vcd
$date
	Sat May 14 22:31:03 2022
$end
$version
	Icarus Verilog
$end
$timescale
	1ns
$end
$scope module FullAdderTB $end
$var wire 1 ! sum $end
$var wire 1 " cout $end
$var reg 1 # a $end
$var reg 1 $ b $end
$var reg 1 % cin $end
$scope module dut1 $end
$var wire 1 # a $end
$var wire 1 $ b $end
$var wire 1 % cin $end
$var wire 1 " cout $end
$var wire 1 ! sum $end
$upscope $end
$upscope $end
$enddefinitions $end
#0
$dumpvars
0%
0$
0#
0"
0!
$end
#10
1!
1#
#20
0#
1$
#30
1"
0!
1#
#40
0"
1!
0#
0$
1%
#50
1"
0!
1#
#60
0#
1$
#70
1!
1#
